{
  "variants": {
    "facing=east,open=false,powered=false": {
      "model": "malum:block/wavemaker",
      "y": 270
    },
    "facing=east,open=false,powered=true": {
      "model": "malum:block/wavemaker",
      "y": 270
    },
    "facing=east,open=true,powered=false": {
      "model": "malum:block/wavemaker_open",
      "y": 270
    },
    "facing=east,open=true,powered=true": {
      "model": "malum:block/wavemaker_open",
      "y": 270
    },
    "facing=north,open=false,powered=false": {
      "model": "malum:block/wavemaker",
      "y": 180
    },
    "facing=north,open=false,powered=true": {
      "model": "malum:block/wavemaker",
      "y": 180
    },
    "facing=north,open=true,powered=false": {
      "model": "malum:block/wavemaker_open",
      "y": 180
    },
    "facing=north,open=true,powered=true": {
      "model": "malum:block/wavemaker_open",
      "y": 180
    },
    "facing=south,open=false,powered=false": {
      "model": "malum:block/wavemaker"
    },
    "facing=south,open=false,powered=true": {
      "model": "malum:block/wavemaker"
    },
    "facing=south,open=true,powered=false": {
      "model": "malum:block/wavemaker_open"
    },
    "facing=south,open=true,powered=true": {
      "model": "malum:block/wavemaker_open"
    },
    "facing=west,open=false,powered=false": {
      "model": "malum:block/wavemaker",
      "y": 90
    },
    "facing=west,open=false,powered=true": {
      "model": "malum:block/wavemaker",
      "y": 90
    },
    "facing=west,open=true,powered=false": {
      "model": "malum:block/wavemaker_open",
      "y": 90
    },
    "facing=west,open=true,powered=true": {
      "model": "malum:block/wavemaker_open",
      "y": 90
    }
  }
}