{
  "ritual_identifier": "malum:grotesque_expulsion",
  "input": {
    "count": 8,
    "ingredient": {
      "item": "malum:rotting_essence"
    }
  },
  "extra_items": [
    {
      "count": 4,
      "ingredient": {
        "item": "minecraft:rotten_flesh"
      }
    },
    {
      "count": 4,
      "ingredient": {
        "item": "malum:grim_talc"
      }
    },
    {
      "count": 2,
      "ingredient": {
        "item": "minecraft:bone"
      }
    },
    {
      "count": 1,
      "ingredient": {
        "item": "minecraft:wither_rose"
      }
    },
    {
      "count": 1,
      "ingredient": {
        "item": "minecraft:wither_skeleton_skull"
      }
    }
  ]
}